ansi_escape_room/__init__.py
ansi_escape_room/back.py
ansi_escape_room/colored.py
ansi_escape_room/colors.py
ansi_escape_room/fore.py
ansi_escape_room/hex.py
ansi_escape_room/style.py
ansi_escape_room-1.5.3.dist-info/LICENSE.txt
ansi_escape_room-1.5.3.dist-info/METADATA
ansi_escape_room-1.5.3.dist-info/WHEEL
ansi_escape_room-1.5.3.dist-info/RECORD
