Metadata-Version: 2.1
Name: ansi-escape-room
Version: 1.5.3
Summary: Simple library for color and formatting to terminal
License: MIT
Keywords: color,colour,paint,ansi,terminal,linux,python
Author: Landon Bouma
Author-email: doblabs@tallybark.com
Maintainer: Tally Bark LLC
Maintainer-email: doblabs@tallybark.com
Requires-Python: >=3.8.1,<4.0.0
Classifier: Development Status :: 5 - Production/Stable
Classifier: Environment :: Console
Classifier: Intended Audience :: End Users/Desktop
Classifier: License :: OSI Approved :: MIT License
Classifier: Natural Language :: English
Classifier: Operating System :: OS Independent
Classifier: Programming Language :: Python :: 3
Classifier: Programming Language :: Python :: 3.9
Classifier: Programming Language :: Python :: 3.10
Classifier: Programming Language :: Python :: 3.11
Classifier: Programming Language :: Python :: 3.12
Classifier: Topic :: Terminals
Provides-Extra: readthedocs
Requires-Dist: sphinx (>=6.2.1,<7.0.0) ; (python_version >= "3.8" and python_version < "3.9") and (extra == "readthedocs")
Requires-Dist: sphinx (>=7.2.6,<8.0.0) ; (python_version >= "3.9" and python_version < "4.0") and (extra == "readthedocs")
Requires-Dist: sphinx-rtd-theme (>=2.0.0rc4,<3.0.0) ; extra == "readthedocs"
Requires-Dist: tomli (>=2.0.1) ; extra == "readthedocs"
Project-URL: documentation, https://ansi-escape-room.readthedocs.io/en/latest
Project-URL: download, https://pypi.org/project/ansi-escape-room/#files
Project-URL: homepage, https://github.com/doblabs/ansi-escape-room#🐰
Project-URL: history, https://github.com/doblabs/ansi-escape-room/blob/release/HISTORY.rst
Project-URL: issues, https://github.com/doblabs/ansi-escape-room/issues
